{
    "title": "MENU",
    "logo": {
        "id": "Logo Id",
        "linkType": "DEFAULT",
        "targetWindow": "SELF",
        "label": "Logo Label",
        "icon": "//cdn.tmobile.com/content/dam/t-mobile/ntm/branding/logos/corporate/tmo-logo-v3.svg",
        "hoverIcon": "LogoHover",
        "linkUrl": [
            {
                "linkText": "T-MOBILE",
                "linkHref": "https://my.t-mobile.com/home",
                "customerType": [
                    "PROSPECT",
                    "TMO-PREVOUSLY-AUTHENTICATED",
                    "TMO-CURRENTLY-AUTHENTICATED"
                ]
            }
        ]
    },
    "navigationLinks": [
        {
            "id": "bill-id",
            "linkType": "DEFAULT",
            "targetWindow": "SELF",
            "label": "Bill",
            "linkUrl": [
                {
                    "linkText": "Bill",
                    "linkHref": "https://my.t-mobile.com/billandpay",
                    "customerType": [
                        "PROSPECT",
                        "TMO-PREVOUSLY-AUTHENTICATED",
                        "TMO-CURRENTLY-AUTHENTICATED"
                    ]
                }
            ]
        },
        {
            "id": "usage-id",
            "linkType": "SINGLE-COLUMN",
            "targetWindow": "SELF",
            "label": "Usage",
            "linkUrl": [
                {
                    "linkText": "Usage",
                    "linkHref": "https://my.t-mobile.com/usage",
                    "customerType": [
                        "PROSPECT",
                        "TMO-PREVOUSLY-AUTHENTICATED",
                        "TMO-CURRENTLY-AUTHENTICATED"
                    ]
                }
            ]
        },
        {
            "id": "account-id",
            "linkType": "DEFAULT",
            "targetWindow": "SELF",
            "label": "Account",
            "linkUrl": [
                {
                    "linkText": "Account",
                    "linkHref": "https://my.t-mobile.com/account/account-overview",
                    "customerType": [
                        "PROSPECT",
                        "TMO-PREVOUSLY-AUTHENTICATED",
                        "TMO-CURRENTLY-AUTHENTICATED"
                    ]
                }
            ]
        },
        {
            "id": "phone-id",
            "linkType": "DEFAULT",
            "targetWindow": "SELF",
            "label": "My phone",
            "linkUrl": [
                {
                    "linkText": "My phone",
                    "linkHref": "https://my.t-mobile.com/myphone/myphonedetails.html",
                    "customerType": [
                        "PROSPECT",
                        "TMO-PREVOUSLY-AUTHENTICATED",
                        "TMO-CURRENTLY-AUTHENTICATED"
                    ]
                }
            ]
        },
        {
            "id": "shop-id",
            "linkType": "DEFAULT",
            "targetWindow": "SELF",
            "label": "Shop",
            "linkUrl": [
                {
                    "linkText": "Shop",
                    "linkHref": "https://my.t-mobile.com/purchase/shop",
                    "customerType": [
                        "PROSPECT",
                        "TMO-PREVOUSLY-AUTHENTICATED",
                        "TMO-CURRENTLY-AUTHENTICATED"
                    ]
                }
            ]
        }
    ],
    "utility": [
        {
            "showInMobileView": false,
            "linkType": "DEFAULT",
            "targetWindow": "SELF",
            "label": "Call us",
            "icon": "mdi-cellphone-android",
            "linkUrl": [
                {
                    "linkText": "Call us",
                    "linkHref": "https://my.t-mobile.com/contact-us",
                    "customerType": [
                        "PROSPECT",
                        "TMO-PREVOUSLY-AUTHENTICATED",
                        "TMO-CURRENTLY-AUTHENTICATED"
                    ]
                }
            ]
        },
        {
            "showInMobileView": true,
            "linkType": "DEFAULT",
            "targetWindow": "SELF",
            "icon": "mdi-phone",
            "linkUrl": [
                {
                    "linkHref": "https://my.t-mobile.com/contact-us",
                    "customerType": [
                        "PROSPECT",
                        "TMO-PREVOUSLY-AUTHENTICATED",
                        "TMO-CURRENTLY-AUTHENTICATED"
                    ]
                }
            ]
        },
        {
            "showInMobileView": false,
            "id": "search",
            "linkType": "DEFAULT",
            "targetWindow": "SELF",
            "label": "Search label",
            "icon": "mdi-magnify",
            "hoverIcon": "mdi-close",
            "linkUrl": [
                {
                    "linkText": "Search",
                    "linkHref": "https://www.t-mobile.com/search?q={querryParam}&unav=mytmo",
                    "customerType": [
                        "PROSPECT",
                        "TMO-PREVOUSLY-AUTHENTICATED",
                        "TMO-CURRENTLY-AUTHENTICATED"
                    ]
                }
            ]
        },
        {
            "showInMobileView": false,
            "id": "login-menu",
            "disabled":false,
            "buttonType": "secondary-black",
            "linkType": "DEFAULT",
            "targetWindow": "SELF",
            "label": "Click login button",
            "icon": "mdi-account",
            "linkUrl": [
              {
                "linkText": "Log in",
                "customerType": [
                   "PROSPECT",
                  "TMO-PREVOUSLY-AUTHENTICATED",
                  "TMO-CURRENTLY-AUTHENTICATED",
                  "PARTNER-PREVOUSLY-AUTHENTICATED",
                  "PARTNER-CURRENTLY-AUTHENTICATED",
                  "TMO-PREVOUSLY-AUTHENTICATED",
                  "TMO-CURRENTLY-AUTHENTICATED",
                  "PARTNER-PREVOUSLY-AUTHENTICATED",
                  "PARTNER-CURRENTLY-AUTHENTICATED"
                ]
              }
            ]
          },
          {
            "showInMobileView": false,
            "buttonType":"primary-black",
            "id": "get-started",
            "disabled":false,
            "linkType": "DEFAULT",
            "targetWindow": "SELF",
            "label": "Click to open My account links",
            "icon": "mdi-account",
            "linkUrl": [
              {
                "linkText": "Get Started",
                "customerType": [
                   "PROSPECT",
                  "TMO-PREVOUSLY-AUTHENTICATED",
                  "TMO-CURRENTLY-AUTHENTICATED",
                  "PARTNER-PREVOUSLY-AUTHENTICATED",
                  "PARTNER-CURRENTLY-AUTHENTICATED",
                  "TMO-PREVOUSLY-AUTHENTICATED",
                  "TMO-CURRENTLY-AUTHENTICATED",
                  "PARTNER-PREVOUSLY-AUTHENTICATED",
                  "PARTNER-CURRENTLY-AUTHENTICATED"
                ]
              }
            ]
          }
    ],
    "userLinks": {
        "labelText": "My account",
        "labelColor": "MAGENTA",
        "mobileIcon": "mdi-account",
        "link": [
            {
                "linkType": "SINGLE-COLUMN",
                "linkUrl": [
                    {
                        "customerType": [
                            "PROSPECT",
                            "TMO-PREVOUSLY-AUTHENTICATED",
                            "TMO-CURRENTLY-AUTHENTICATED"
                        ],
                        "childLinks": [
                            {
                                "categorizedlink": [
                                    {
                                        "id": "Profile",
                                        "linkType": "DEFAULT",
                                        "targetWindow": "NONE",
                                        "label": "Profile",
                                        "icon": "Profile Icon",
                                        "hoverIcon": "Profile Hover",
                                        "linkUrl": [
                                            {
                                                "linkText": "Profile",
                                                "linkHref": "https://my.t-mobile.com/account/profile",
                                                "customerType": [
                                                    "PROSPECT",
                                                    "TMO-PREVOUSLY-AUTHENTICATED",
                                                    "TMO-CURRENTLY-AUTHENTICATED"
                                                ]
                                            }
                                        ]
                                    },
                                    {
                                        "linkType": "DEFAULT",
                                        "targetWindow": "SELF",
                                        "label": "Account history",
                                        "linkUrl": [
                                            {
                                                "linkText": "Account history",
                                                "linkHref": "https://my.t-mobile.com/accounthistory",
                                                "customerType": [
                                                    "PROSPECT",
                                                    "TMO-PREVOUSLY-AUTHENTICATED",
                                                    "TMO-CURRENTLY-AUTHENTICATED"
                                                ]
                                            }
                                        ]
                                    },
                                    {
                                        "id": "switch-account",
                                        "linkType": "DEFAULT",
                                        "targetWindow": "SELF",
                                        "label": "Switch account",
                                        "linkUrl": [
                                            {
                                                "linkText": "Switch account",
                                                "linkHref": "https://account.t-mobile.com/accountchooser",
                                                "customerType": [
                                                    "PROSPECT",
                                                    "TMO-PREVOUSLY-AUTHENTICATED",
                                                    "TMO-CURRENTLY-AUTHENTICATED"
                                                ]
                                            }
                                        ]
                                    },
                                    {
                                        "id": "logout",
                                        "linkType": "DEFAULT",
                                        "targetWindow": "SELF",
                                        "label": "Logout Label",
                                        "icon": "Logout Icon",
                                        "hoverIcon": "Logout Hover",
                                        "linkUrl": [
                                            {
                                                "linkText": "Logout",
                                                "customerType": [
                                                    "TMO-PREVOUSLY-AUTHENTICATED",
                                                    "TMO-CURRENTLY-AUTHENTICATED"
                                                ]
                                            }
                                        ]
                                    }
                                ]
                            }
                        ]
                    }
                ]
            }
        ]
    },
    "search": {
        "searchURL": "https://content.atomz.com/autocomplete/sp10/05/0e/bc",
        "quickLinksLabel": "Quick links",
        "topSearchesLabel": "Top searches",
        "quickLinks": [
            {
                "linkText": "Change sim",
                "linkHref": "https://my.t-mobile.com/myphone/changesim.html",
                "targetWindow": "SELF"
            },
            {
                "linkText": "Paperless billing",
                "linkHref": "https://my.t-mobile.com/account/profile/billing_payment/paperless_billing",
                "targetWindow": "SELF"
            },
            {
                "linkText": "Accessories",
                "linkHref": "https://my.t-mobile.com/shop/accessories",
                "targetWindow": "SELF"
            }
        ],
        "searchSuggestions": [
            {
                "linkText": "iPhone 11",
                "linkHref": "https://www.t-mobile.com/search?q=iphone%2011&unav=mytmo",
                "targetWindow": "SELF"
            },
            {
                "linkText": "iPhone 11 Pro",
                "linkHref": "https://www.t-mobile.com/search?q=iphone%2011%20pro&unav=mytmo",
                "targetWindow": "SELF"
            },
            {
                "linkText": "iPhone 11 Pro Max",
                "linkHref": "https://www.t-mobile.com/search?q=iphone%2011%20pro%20max&unav=mytmo",
                "targetWindow": "SELF"
            },
            {
                "linkText": "Airpods",
                "linkHref": "https://www.t-mobile.com/search?q=airpods&unav=mytmo",
                "targetWindow": "SELF"
            }
        ],
        "enableNewDropDown": true,
        "enableDefaultScript": true,
        "searchHint": "Search",
        "maxPredictive": 5
    }
}